{
	"backtraceGraph" : 
	{
		"commands" : 
		[
			"INSTALL"
		],
		"files" : 
		[
			"include/bullet3/examples/OpenGLWindow/CMakeLists.txt"
		],
		"nodes" : 
		[
			{
				"file" : 0
			},
			{
				"command" : 0,
				"file" : 0,
				"line" : 77,
				"parent" : 0
			}
		]
	},
	"installers" : 
	[
		{
			"backtrace" : 1,
			"component" : "Unspecified",
			"destination" : "lib",
			"paths" : 
			[
				"include/bullet3/examples/OpenGLWindow/libOpenGLWindowd.so"
			],
			"targetId" : "OpenGLWindow::@7cb45858d5b3deb21b85",
			"targetIndex" : 33,
			"type" : "target"
		}
	],
	"paths" : 
	{
		"build" : "include/bullet3/examples/OpenGLWindow",
		"source" : "include/bullet3/examples/OpenGLWindow"
	}
}
